autoeis/__init__.py
autoeis/__main__.py
autoeis/cli.py
autoeis/cli_pyjulia.py
autoeis/core.py
autoeis/io.py
autoeis/julia_helpers.py
autoeis/julia_helpers_pyjulia.py
autoeis/juliapkg.json
autoeis/legacy.py
autoeis/metrics.py
autoeis/models.py
autoeis/parser.py
autoeis/utils.py
autoeis/version.py
autoeis/visualization.py
autoeis/assets/battery_data.npy
autoeis/assets/circuits_filtered.csv
autoeis/assets/circuits_unfiltered.csv
autoeis/assets/test_data.txt
autoeis-0.0.40.dist-info/METADATA
autoeis-0.0.40.dist-info/WHEEL
autoeis-0.0.40.dist-info/licenses/LICENSE
autoeis-0.0.40.dist-info/RECORD
