Metadata-Version: 2.4
Name: autoeis
Version: 0.0.40
Summary: A tool for automated EIS analysis by proposing statistically plausible ECMs.
Project-URL: Homepage, https://github.com/AUTODIAL/AutoEIS
Project-URL: Repository, https://github.com/AUTODIAL/AutoEIS
Project-URL: Bug Tracker, https://github.com/AUTODIAL/AutoEIS/issues
Project-URL: Documentation, https://autodial.github.io/AutoEIS
Author-email: Runze Zhang <runzee.zhang@mail.utoronto.ca>, Amin Sadeghi <amin.sadeghi@live.com>, Robert Black <robert.black@nrc-cnrc.gc.ca>, Jason Hattrick-Simpers <jason.hattrick.simpers@utoronto.ca>
Maintainer-email: Amin Sadeghi <amin.sadeghi@live.com>
License-Expression: MIT
License-File: LICENSE
Keywords: bayesian inference,electrochemical impedance spectroscopy,equivalent circuit model,evolutionary algorithm
Classifier: License :: OSI Approved :: MIT License
Classifier: Operating System :: OS Independent
Classifier: Programming Language :: Python :: 3
Requires-Python: <3.13,>=3.10
Requires-Dist: arviz
Requires-Dist: click
Requires-Dist: deprecated
Requires-Dist: dill
Requires-Dist: impedance
Requires-Dist: ipykernel
Requires-Dist: ipython
Requires-Dist: ipywidgets
Requires-Dist: jax<0.7.0
Requires-Dist: jinja2>=3.1.2
Requires-Dist: juliacall
Requires-Dist: juliapkg
Requires-Dist: matplotlib
Requires-Dist: mpire[dill]
Requires-Dist: numexpr
Requires-Dist: numpy<2
Requires-Dist: numpyro
Requires-Dist: pandas
Requires-Dist: psutil
Requires-Dist: pyparsing>=3
Requires-Dist: python-box
Requires-Dist: rich
Requires-Dist: scikit-learn>=1.4
Requires-Dist: seaborn
Requires-Dist: tqdm
Provides-Extra: lcapy
Requires-Dist: lcapy; extra == 'lcapy'
